easysubpub/__init__.py
easysubpub/__main__.py
easysubpub/client.py
easysubpub/pub.py
easysubpub/sub.py
easysubpub-0.0.2.dist-info/LICENSE
easysubpub-0.0.2.dist-info/METADATA
easysubpub-0.0.2.dist-info/WHEEL
easysubpub-0.0.2.dist-info/top_level.txt
easysubpub-0.0.2.dist-info/RECORD
